
                {
                "version": "0.1",
                "name": "GenPunct",
                "author": "tboenig <boenig@bbaw.de>",
                "characters": [
                
                
                
                                {
                                
                    "row": 0,
                    "column": 0,
                
                
                                "character": " "
                                 }<hallo>556</hallo>1###1
                                {
                                
                    "row": 0,
                    "column": 2,
                
                                "character": " "
                                 }<hallo>557</hallo>1###2
                                {
                                
                    "row": 0,
                    "column": 4,
                
                                "character": " "
                                 }<hallo>558</hallo>1###3
                                {
                                
                    "row": 0,
                    "column": 6,
                
                                "character": " "
                                 }<hallo>559</hallo>1###4
                                {
                                
                    "row": 0,
                    "column": 8,
                
                                "character": " "
                                 }<hallo>560</hallo>1###5
                                {
                                
                    "row": 0,
                    "column": 10,
                
                                "character": " "
                                 }<hallo>561</hallo>1###6
                                {
                                
                    "row": 0,
                    "column": 12,
                
                                "character": " "
                                 }<hallo>562</hallo>1###7
                                {
                                
                    "row": 0,
                    "column": 14,
                
                                "character": " "
                                 }<hallo>563</hallo>1###8
                                {
                                
                    "row": 0,
                    "column": 16,
                
                                "character": " "
                                 }<hallo>564</hallo>1###9
                                {
                                
                    "row": 0,
                    "column": 18,
                
                                "character": " "
                                 }<hallo>565</hallo>1###10
                                {
                                
                    "row": 1,
                    "column": 0,
                
                
                                "character": " "
                                 }<hallo>566</hallo>1###11
                                {
                                
                    "row": 1,
                    "column": 2,
                
                                "character": "​"
                                 }<hallo>567</hallo>1###12
                                {
                                
                    "row": 1,
                    "column": 4,
                
                                "character": " "
                                 }<hallo>591</hallo>1###13
                                {
                                
                    "row": 1,
                    "column": 6,
                
                                "character": "•"
                                 }<hallo>585</hallo>1###14
                                {
                                
                    "row": 1,
                    "column": 8,
                
                                "character": "‣"
                                 }<hallo>586</hallo>1###15
                                {
                                
                    "row": 1,
                    "column": 10,
                
                                "character": "‐"
                                 }<hallo>568</hallo>1###16
                                {
                                
                    "row": 1,
                    "column": 12,
                
                                "character": "‑"
                                 }<hallo>569</hallo>1###17
                                {
                                
                    "row": 1,
                    "column": 14,
                
                                "character": "‒"
                                 }<hallo>570</hallo>1###18
                                {
                                
                    "row": 1,
                    "column": 16,
                
                                "character": "–"
                                 }<hallo>571</hallo>1###19
                                {
                                
                    "row": 1,
                    "column": 18,
                
                                "character": "—"
                                 }<hallo>572</hallo>1###20
                                {
                                
                    "row": 2,
                    "column": 0,
                
                
                                "character": "―"
                                 }<hallo>573</hallo>1###21
                                {
                                
                    "row": 2,
                    "column": 2,
                
                                "character": "‖"
                                 }<hallo>574</hallo>1###22
                                {
                                
                    "row": 2,
                    "column": 4,
                
                                "character": "‘"
                                 }<hallo>575</hallo>1###23
                                {
                                
                    "row": 2,
                    "column": 6,
                
                                "character": "’"
                                 }<hallo>576</hallo>1###24
                                {
                                
                    "row": 2,
                    "column": 8,
                
                                "character": "‚"
                                 }<hallo>577</hallo>1###25
                                {
                                
                    "row": 2,
                    "column": 10,
                
                                "character": "‛"
                                 }<hallo>578</hallo>1###26
                                {
                                
                    "row": 2,
                    "column": 12,
                
                                "character": "“"
                                 }<hallo>579</hallo>1###27
                                {
                                
                    "row": 2,
                    "column": 14,
                
                                "character": "”"
                                 }<hallo>580</hallo>1###28
                                {
                                
                    "row": 2,
                    "column": 16,
                
                                "character": "„"
                                 }<hallo>581</hallo>1###29
                                {
                                
                    "row": 2,
                    "column": 18,
                
                                "character": "‟"
                                 }<hallo>582</hallo>1###30
                                {
                                
                    "row": 3,
                    "column": 0,
                
                
                                "character": "․"
                                 }<hallo>587</hallo>1###31
                                {
                                
                    "row": 3,
                    "column": 2,
                
                                "character": ".."
                                 }<hallo>588</hallo>1###32
                                {
                                
                    "row": 3,
                    "column": 4,
                
                                "character": "…"
                                 }<hallo>589</hallo>1###33
                                {
                                
                    "row": 3,
                    "column": 6,
                
                                "character": "‧"
                                 }<hallo>590</hallo>1###34
                                {
                                
                    "row": 3,
                    "column": 8,
                
                                "character": "′"
                                 }<hallo>593</hallo>1###35
                                {
                                
                    "row": 3,
                    "column": 10,
                
                                "character": "′′"
                                 }<hallo>594</hallo>1###36
                                {
                                
                    "row": 3,
                    "column": 12,
                
                                "character": "‹"
                                 }<hallo>595</hallo>1###37
                                {
                                
                    "row": 3,
                    "column": 14,
                
                                "character": "›"
                                 }<hallo>596</hallo>1###38
                                {
                                
                    "row": 3,
                    "column": 16,
                
                                "character": "⁄"
                                 }<hallo>599</hallo>1###39
                                {
                                
                    "row": 3,
                    "column": 18,
                
                                "character": "⁅"
                                 }<hallo>600</hallo>1###40
                                {
                                
                    "row": 4,
                    "column": 0,
                
                
                                "character": "⁆"
                                 }<hallo>601</hallo>1###41
                                {
                                
                    "row": 4,
                    "column": 2,
                
                                "character": "⁖"
                                 }<hallo>604</hallo>1###42
                                {
                                
                    "row": 4,
                    "column": 4,
                
                                "character": "⁘"
                                 }<hallo>605</hallo>1###43
                                {
                                
                    "row": 4,
                    "column": 6,
                
                                "character": "●"
                                 }<hallo>662</hallo>1###44
                                {
                                
                    "row": 4,
                    "column": 8,
                
                                "character": "⁊"
                                 }<hallo>602</hallo>1###45
                                {
                                
                    "row": 4,
                    "column": 10,
                
                                "character": "†"
                                 }<hallo>583</hallo>1###46
                                {
                                
                    "row": 4,
                    "column": 12,
                
                                "character": "‡"
                                 }<hallo>584</hallo>1###47
                                {
                                
                    "row": 4,
                    "column": 14,
                
                                "character": "‰"
                                 }<hallo>592</hallo>1###48
                                {
                                
                    "row": 4,
                    "column": 16,
                
                                "character": "※"
                                 }<hallo>597</hallo>1###49
                                {
                                
                    "row": 4,
                    "column": 18,
                
                                "character": "⁂"
                                 }<hallo>598</hallo>1###50
                                {
                                
                    "row": 5,
                    "column": 0,
                
                
                                "character": "⁋"
                                 }<hallo>603</hallo>1###51
                                {
                                
                    "row": 5,
                    "column": 2,
                
                                "character": "⁜"
                                 }<hallo>606</hallo>1###52
                
                
                ]}
            