
                {
                "version": "0.1",
                "name": "IPAExt",
                "author": "tboenig boenig@bbaw.de",
                "characters": [
                
                
                
                                {
                                
        Hallo
    
                                
                                "row": 1,
                                "column": 3,
                                "character": "ʙ
                                 }
                            
                                {
                                
        Hallo
    
                                
                                "row": 1,
                                "column": 3,
                                "character": "ɖ
                                 }
                            
                                {
                                
        Hallo
    
                                
                                "row": 1,
                                "column": 3,
                                "character": "ə
                                 }
                            
                                {
                                
        Hallo
    
                                
                                "row": 1,
                                "column": 3,
                                "character": "ɡ
                                 }
                            
                                {
                                
        Hallo
    
                                
                                "row": 1,
                                "column": 3,
                                "character": "ɢ
                                 }
                            
                                {
                                
        Hallo
    
                                
                                "row": 1,
                                "column": 3,
                                "character": "ɦ
                                 }
                            
                                {
                                
        Hallo
    
                                
                                "row": 1,
                                "column": 3,
                                "character": "ʜ
                                 }
                            
                                {
                                
        Hallo
    
                                
                                "row": 1,
                                "column": 3,
                                "character": "ɨ
                                 }
                            
                                {
                                
        Hallo
    
                                
                                "row": 1,
                                "column": 3,
                                "character": "ɪ
                                 }
                            
                                {
                                
        Hallo
    
                                
                                "row": 1,
                                "column": 3,
                                "character": "ɟ
                                 }
                            
                                {
                                
        Hallo
    
                                
                                "row": 1,
                                "column": 3,
                                "character": "ʟ
                                 }
                            
                                {
                                
        Hallo
    
                                
                                "row": 1,
                                "column": 3,
                                "character": "ɯ
                                 }
                            
                                {
                                
        Hallo
    
                                
                                "row": 1,
                                "column": 3,
                                "character": "ɲ
                                 }
                            
                                {
                                
        Hallo
    
                                
                                "row": 1,
                                "column": 3,
                                "character": "ɴ
                                 }
                            
                                {
                                
        Hallo
    
                                
                                "row": 1,
                                "column": 3,
                                "character": "ɔ
                                 }
                            
                                {
                                
        Hallo
    
                                
                                "row": 1,
                                "column": 3,
                                "character": "ɶ
                                 }
                            
                                {
                                
        Hallo
    
                                
                                "row": 1,
                                "column": 3,
                                "character": "ɼ
                                 }
                            
                                {
                                
        Hallo
    
                                
                                "row": 1,
                                "column": 3,
                                "character": "ʀ
                                 }
                            
                                {
                                
        Hallo
    
                                
                                "row": 1,
                                "column": 3,
                                "character": "ʉ
                                 }
                            
                                {
                                
        Hallo
    
                                
                                "row": 1,
                                "column": 3,
                                "character": "ʏ
                                 }
                            
                                {
                                
        Hallo
    
                                
                                "row": 1,
                                "column": 3,
                                "character": "ʒ
                                 }
                            
                
                
                ]}
            