
                {
                "version": "0.1",
                "name": "Lat1Suppl",
                "author": "tboenig &lt;boenig@bbaw.de&gt;",
                "characters": [
                
                
                
                                {
                                
                                "character": "ª"
                                 }
                            
                                {
                                
                                "character": "À"
                                 }
                            
                                {
                                
                                "character": "Á"
                                 }
                            
                                {
                                
                                "character": "Â"
                                 }
                            
                                {
                                
                                "character": "Ã"
                                 }
                            
                                {
                                
                                "character": "Ä"
                                 }
                            
                                {
                                
                                "character": "Å"
                                 }
                            
                                {
                                
                                "character": "Æ"
                                 }
                            
                                {
                                
                                "character": "à"
                                 }
                            
                                {
                                
                                "character": "á"
                                 }
                            
                                {
                                
                                "character": "â"
                                 }
                            
                                {
                                
                                "character": "ã"
                                 }
                            
                                {
                                
                                "character": "ä"
                                 }
                            
                                {
                                
                                "character": "å"
                                 }
                            
                                {
                                
                                "character": "æ"
                                 }
                            
                                {
                                
                                "character": "Ç"
                                 }
                            
                                {
                                
                                "character": "ç"
                                 }
                            
                                {
                                
                                "character": "Ð"
                                 }
                            
                                {
                                
                                "character": "ð"
                                 }
                            
                                {
                                
                                "character": "È"
                                 }
                            
                                {
                                
                                "character": "É"
                                 }
                            
                                {
                                
                                "character": "Ê"
                                 }
                            
                                {
                                
                                "character": "Ë"
                                 }
                            
                                {
                                
                                "character": "è"
                                 }
                            
                                {
                                
                                "character": "é"
                                 }
                            
                                {
                                
                                "character": "ê"
                                 }
                            
                                {
                                
                                "character": "ë"
                                 }
                            
                                {
                                
                                "character": "Ì"
                                 }
                            
                                {
                                
                                "character": "Í"
                                 }
                            
                                {
                                
                                "character": "Î"
                                 }
                            
                                {
                                
                                "character": "Ï"
                                 }
                            
                                {
                                
                                "character": "ì"
                                 }
                            
                                {
                                
                                "character": "í"
                                 }
                            
                                {
                                
                                "character": "î"
                                 }
                            
                                {
                                
                                "character": "ï"
                                 }
                            
                                {
                                
                                "character": "Ñ"
                                 }
                            
                                {
                                
                                "character": "ñ"
                                 }
                            
                                {
                                
                                "character": "º"
                                 }
                            
                                {
                                
                                "character": "Ò"
                                 }
                            
                                {
                                
                                "character": "Ó"
                                 }
                            
                                {
                                
                                "character": "Ô"
                                 }
                            
                                {
                                
                                "character": "Õ"
                                 }
                            
                                {
                                
                                "character": "Ö"
                                 }
                            
                                {
                                
                                "character": "Ø"
                                 }
                            
                                {
                                
                                "character": "ò"
                                 }
                            
                                {
                                
                                "character": "ó"
                                 }
                            
                                {
                                
                                "character": "ô"
                                 }
                            
                                {
                                
                                "character": "õ"
                                 }
                            
                                {
                                
                                "character": "ö"
                                 }
                            
                                {
                                
                                "character": "ø"
                                 }
                            
                                {
                                
                                "character": "ß"
                                 }
                            
                                {
                                
                                "character": "Ù"
                                 }
                            
                                {
                                
                                "character": "Ú"
                                 }
                            
                                {
                                
                                "character": "Û"
                                 }
                            
                                {
                                
                                "character": "Ü"
                                 }
                            
                                {
                                
                                "character": "ù"
                                 }
                            
                                {
                                
                                "character": "ú"
                                 }
                            
                                {
                                
                                "character": "û"
                                 }
                            
                                {
                                
                                "character": "ü"
                                 }
                            
                                {
                                
                                "character": "Ý"
                                 }
                            
                                {
                                
                                "character": "ý"
                                 }
                            
                                {
                                
                                "character": "ÿ"
                                 }
                            
                                {
                                
                                "character": " "
                                 }
                            
                                {
                                
                                "character": "­"
                                 }
                            
                                {
                                
                                "character": "²"
                                 }
                            
                                {
                                
                                "character": "³"
                                 }
                            
                                {
                                
                                "character": "¹"
                                 }
                            
                                {
                                
                                "character": "¼"
                                 }
                            
                                {
                                
                                "character": "½"
                                 }
                            
                                {
                                
                                "character": "¾"
                                 }
                            
                                {
                                
                                "character": "¡"
                                 }
                            
                                {
                                
                                "character": "¦"
                                 }
                            
                                {
                                
                                "character": "«"
                                 }
                            
                                {
                                
                                "character": "·"
                                 }
                            
                                {
                                
                                "character": "»"
                                 }
                            
                                {
                                
                                "character": "¿"
                                 }
                            
                                {
                                
                                "character": "¨"
                                 }
                            
                                {
                                
                                "character": "¯"
                                 }
                            
                                {
                                
                                "character": "´"
                                 }
                            
                                {
                                
                                "character": "¸"
                                 }
                            
                                {
                                
                                "character": "¢"
                                 }
                            
                                {
                                
                                "character": "£"
                                 }
                            
                                {
                                
                                "character": "¤"
                                 }
                            
                                {
                                
                                "character": "¥"
                                 }
                            
                                {
                                
                                "character": "§"
                                 }
                            
                                {
                                
                                "character": "©"
                                 }
                            
                                {
                                
                                "character": "¬"
                                 }
                            
                                {
                                
                                "character": "®"
                                 }
                            
                                {
                                
                                "character": "°"
                                 }
                            
                                {
                                
                                "character": "±"
                                 }
                            
                                {
                                
                                "character": "μ"
                                 }
                            
                                {
                                
                                "character": "¶"
                                 }
                            
                                {
                                
                                "character": "×"
                                 }
                            
                                {
                                
                                "character": "÷"
                                 }
                            
                                {
                                
                                "character": "Þ"
                                 }
                            
                                {
                                
                                "character": "þ"
                                 }
                             {bksp}"]
                    
                    
                
                
                
                ]}
            