
                {
                "version": "0.1",
                "name": "LatExtC",
                "author": "tboenig boenig@bbaw.de",
                "characters": [
                
                
                
                                {
                                
            number: 11
                                "character": "Ⱶ
                                 }
                            
                                {
                                
            number: 2
                                "character": "ⱶ
                                 }
                            
                                {
                                
            number: 3
                                "character": "ⱽ
                                 }
                            
                
                
                ]}
            