
                {
                "version": "0.1",
                "name": "LatExtA",
                "author": "tboenig boenig@bbaw.de",
                "characters": [
                
                
                
                                {
                                
            number: 1
                                
                                "row": 1,
                                "column": 3,
                                "character": "Ā
                                 }
                            
                                {
                                
            number: 2
                                
                                "row": 1,
                                "column": 3,
                                "character": "ā
                                 }
                            
                                {
                                
            number: 3
                                
                                "row": 1,
                                "column": 3,
                                "character": "Ă
                                 }
                            
                                {
                                
            number: 4
                                
                                "row": 1,
                                "column": 3,
                                "character": "ă
                                 }
                            
                                {
                                
            number: 5
                                
                                "row": 1,
                                "column": 3,
                                "character": "Ą
                                 }
                            
                                {
                                
            number: 6
                                
                                "row": 1,
                                "column": 3,
                                "character": "ą
                                 }
                            
                                {
                                
            number: 7
                                
                                "row": 1,
                                "column": 3,
                                "character": "Ć
                                 }
                            
                                {
                                
            number: 8
                                
                                "row": 1,
                                "column": 3,
                                "character": "ć
                                 }
                            
                                {
                                
            number: 9
                                
                                "row": 1,
                                "column": 3,
                                "character": "Ċ
                                 }
                            
                                {
                                
            number: 10
                                
                                "row": 1,
                                "column": 3,
                                "character": "ċ
                                 }
                            
                                {
                                
            number: 11
                                
                                "row": 1,
                                "column": 3,
                                "character": "Đ
                                 }
                            
                                {
                                
            number: 12
                                
                                "row": 1,
                                "column": 3,
                                "character": "đ
                                 }
                            
                                {
                                
            number: 13
                                
                                "row": 1,
                                "column": 3,
                                "character": "Ē
                                 }
                            
                                {
                                
            number: 14
                                
                                "row": 1,
                                "column": 3,
                                "character": "ē
                                 }
                            
                                {
                                
            number: 15
                                
                                "row": 1,
                                "column": 3,
                                "character": "Ĕ
                                 }
                            
                                {
                                
            number: 16
                                
                                "row": 1,
                                "column": 3,
                                "character": "ĕ
                                 }
                            
                                {
                                
            number: 17
                                
                                "row": 1,
                                "column": 3,
                                "character": "Ė
                                 }
                            
                                {
                                
            number: 18
                                
                                "row": 1,
                                "column": 3,
                                "character": "ė
                                 }
                            
                                {
                                
            number: 19
                                
                                "row": 1,
                                "column": 3,
                                "character": "Ę
                                 }
                            
                                {
                                
            number: 20
                                
                                "row": 1,
                                "column": 3,
                                "character": "ę
                                 }
                            
                                {
                                
            number: 21
                                
                                "row": 1,
                                "column": 3,
                                "character": "Ġ
                                 }
                            
                                {
                                
            number: 22
                                
                                "row": 1,
                                "column": 3,
                                "character": "ġ
                                 }
                            
                                {
                                
            number: 23
                                
                                "row": 1,
                                "column": 3,
                                "character": "ħ
                                 }
                            
                                {
                                
            number: 24
                                
                                "row": 1,
                                "column": 3,
                                "character": "Ī
                                 }
                            
                                {
                                
            number: 25
                                
                                "row": 1,
                                "column": 3,
                                "character": "ī
                                 }
                            
                                {
                                
            number: 26
                                
                                "row": 1,
                                "column": 3,
                                "character": "Ĭ
                                 }
                            
                                {
                                
            number: 27
                                
                                "row": 1,
                                "column": 3,
                                "character": "ĭ
                                 }
                            
                                {
                                
            number: 28
                                
                                "row": 1,
                                "column": 3,
                                "character": "Į
                                 }
                            
                                {
                                
            number: 29
                                
                                "row": 1,
                                "column": 3,
                                "character": "į
                                 }
                            
                                {
                                
            number: 30
                                
                                "row": 1,
                                "column": 3,
                                "character": "İ
                                 }
                            
                                {
                                
            number: 31
                                
                                "row": 1,
                                "column": 3,
                                "character": "ı
                                 }
                            
                                {
                                
            number: 32
                                
                                "row": 1,
                                "column": 3,
                                "character": "IJ
                                 }
                            
                                {
                                
            number: 33
                                
                                "row": 1,
                                "column": 3,
                                "character": "ij
                                 }
                            
                                {
                                
            number: 34
                                
                                "row": 1,
                                "column": 3,
                                "character": "Ĺ
                                 }
                            
                                {
                                
            number: 35
                                
                                "row": 1,
                                "column": 3,
                                "character": "ĺ
                                 }
                            
                                {
                                
            number: 36
                                
                                "row": 1,
                                "column": 3,
                                "character": "Ł
                                 }
                            
                                {
                                
            number: 37
                                
                                "row": 1,
                                "column": 3,
                                "character": "ł
                                 }
                            
                                {
                                
            number: 38
                                
                                "row": 1,
                                "column": 3,
                                "character": "Ń
                                 }
                            
                                {
                                
            number: 39
                                
                                "row": 1,
                                "column": 3,
                                "character": "ń
                                 }
                            
                                {
                                
            number: 40
                                
                                "row": 1,
                                "column": 3,
                                "character": "Ŋ
                                 }
                            
                                {
                                
            number: 41
                                
                                "row": 1,
                                "column": 3,
                                "character": "ŋ
                                 }
                            
                                {
                                
            number: 42
                                
                                "row": 1,
                                "column": 3,
                                "character": "Ō
                                 }
                            
                                {
                                
            number: 43
                                
                                "row": 1,
                                "column": 3,
                                "character": "ō
                                 }
                            
                                {
                                
            number: 44
                                
                                "row": 1,
                                "column": 3,
                                "character": "Ŏ
                                 }
                            
                                {
                                
            number: 45
                                
                                "row": 1,
                                "column": 3,
                                "character": "ŏ
                                 }
                            
                                {
                                
            number: 46
                                
                                "row": 1,
                                "column": 3,
                                "character": "Ő
                                 }
                            
                                {
                                
            number: 47
                                
                                "row": 1,
                                "column": 3,
                                "character": "ő
                                 }
                            
                                {
                                
            number: 48
                                
                                "row": 1,
                                "column": 3,
                                "character": "Œ
                                 }
                            
                                {
                                
            number: 49
                                
                                "row": 1,
                                "column": 3,
                                "character": "œ
                                 }
                            
                                {
                                
            number: 50
                                
                                "row": 1,
                                "column": 3,
                                "character": "Ŕ
                                 }
                            
                                {
                                
            number: 51
                                
                                "row": 1,
                                "column": 3,
                                "character": "ŕ
                                 }
                            
                                {
                                
            number: 52
                                
                                "row": 1,
                                "column": 3,
                                "character": "Ś
                                 }
                            
                                {
                                
            number: 53
                                
                                "row": 1,
                                "column": 3,
                                "character": "ś
                                 }
                            
                                {
                                
            number: 54
                                
                                "row": 1,
                                "column": 3,
                                "character": "ſ
                                 }
                            
                                {
                                
            number: 55
                                
                                "row": 1,
                                "column": 3,
                                "character": "Ū
                                 }
                            
                                {
                                
            number: 56
                                
                                "row": 1,
                                "column": 3,
                                "character": "ū
                                 }
                            
                                {
                                
            number: 57
                                
                                "row": 1,
                                "column": 3,
                                "character": "Ŭ
                                 }
                            
                                {
                                
            number: 58
                                
                                "row": 1,
                                "column": 3,
                                "character": "ŭ
                                 }
                            
                                {
                                
            number: 59
                                
                                "row": 1,
                                "column": 3,
                                "character": "Ů
                                 }
                            
                                {
                                
            number: 60
                                
                                "row": 1,
                                "column": 3,
                                "character": "ů
                                 }
                            
                                {
                                
            number: 61
                                
                                "row": 1,
                                "column": 3,
                                "character": "Ű
                                 }
                            
                                {
                                
            number: 62
                                
                                "row": 1,
                                "column": 3,
                                "character": "ű
                                 }
                            
                                {
                                
            number: 63
                                
                                "row": 1,
                                "column": 3,
                                "character": "Ų
                                 }
                            
                                {
                                
            number: 64
                                
                                "row": 1,
                                "column": 3,
                                "character": "ų
                                 }
                            
                                {
                                
            number: 65
                                
                                "row": 1,
                                "column": 3,
                                "character": "Ŵ
                                 }
                            
                                {
                                
            number: 66
                                
                                "row": 1,
                                "column": 3,
                                "character": "ŵ
                                 }
                            
                                {
                                
            number: 67
                                
                                "row": 1,
                                "column": 3,
                                "character": "Ŷ
                                 }
                            
                                {
                                
            number: 68
                                
                                "row": 1,
                                "column": 3,
                                "character": "ŷ
                                 }
                            
                                {
                                
            number: 69
                                
                                "row": 1,
                                "column": 3,
                                "character": "Ÿ
                                 }
                            
                                {
                                
            number: 70
                                
                                "row": 1,
                                "column": 3,
                                "character": "Ż
                                 }
                            
                                {
                                
            number: 71
                                
                                "row": 1,
                                "column": 3,
                                "character": "ż
                                 }
                            
                
                
                ]}
            