
                {
                "version": "0.1",
                "name": "LatExtE",
                "author": "tboenig boenig@bbaw.de",
                "characters": [
                
                
                
                                {
                                
                                "row": 1,
                                "column": 3,
                                "character": "ꭗ
                                 }
                            
                ]}
            