
                {
                "version": "0.1",
                "name": "PUA-39",
                "author": "tboenig boenig@bbaw.de",
                "characters": [
                
                
                
                                {
                                
                                "number:" 815
                                "row": 1,
                                "column": 3,
                                "character": "
                                 }
                            
                                {
                                
                                "number:" 932
                                "row": 1,
                                "column": 3,
                                "character": "
                                 }
                            
                                {
                                
                                "number:" 841
                                "row": 1,
                                "column": 3,
                                "character": "
                                 }
                            
                                {
                                
                                "number:" 970
                                "row": 1,
                                "column": 3,
                                "character": "
                                 }
                            
                ]}
            